datacube/__init__.py
datacube/_version.py
datacube/config.py
datacube/helpers.py
datacube/migration.py
datacube/py.typed
datacube/api/__init__.py
datacube/api/core.py
datacube/api/grid_workflow.py
datacube/api/query.py
datacube/cfg/__init__.py
datacube/cfg/api.py
datacube/cfg/cfg.py
datacube/cfg/exceptions.py
datacube/cfg/opt.py
datacube/cfg/utils.py
datacube/drivers/__init__.py
datacube/drivers/_tools.py
datacube/drivers/_types.py
datacube/drivers/datasource.py
datacube/drivers/driver_cache.py
datacube/drivers/indexes.py
datacube/drivers/readers.py
datacube/drivers/writers.py
datacube/drivers/netcdf/__init__.py
datacube/drivers/netcdf/_write.py
datacube/drivers/netcdf/driver.py
datacube/drivers/netcdf/writer.py
datacube/drivers/postgis/__init__.py
datacube/drivers/postgis/_api.py
datacube/drivers/postgis/_connections.py
datacube/drivers/postgis/_core.py
datacube/drivers/postgis/_fields.py
datacube/drivers/postgis/_schema.py
datacube/drivers/postgis/_spatial.py
datacube/drivers/postgis/alembic.ini
datacube/drivers/postgis/sql.py
datacube/drivers/postgis/alembic/README.md
datacube/drivers/postgis/alembic/env.py
datacube/drivers/postgis/alembic/script.py.mako
datacube/drivers/postgis/alembic/versions/01fa1abedd6d_fix_ownerships_and_permissions.py
datacube/drivers/postgis/alembic/versions/18afe14f2816_updated_column.py
datacube/drivers/postgis/alembic/versions/48fb71ece268_initial_revision.py
datacube/drivers/postgis/alembic/versions/610f32dca3cb_added_archived_indexed.py
datacube/drivers/postgis/alembic/versions/d27eed82e1f6_remove_datasetlocation_table.py
datacube/drivers/postgis/samples/range-tests-explicit.sql
datacube/drivers/postgis/samples/range-tests-scalar.sql
datacube/drivers/postgis/samples/range-tests-view.sql
datacube/drivers/postgres/__init__.py
datacube/drivers/postgres/_api.py
datacube/drivers/postgres/_connections.py
datacube/drivers/postgres/_core.py
datacube/drivers/postgres/_dynamic.py
datacube/drivers/postgres/_fields.py
datacube-1.9.12.dist-info/licenses/LICENSE
datacube-1.9.12.dist-info/METADATA
datacube-1.9.12.dist-info/WHEEL
datacube-1.9.12.dist-info/entry_points.txt
datacube-1.9.12.dist-info/top_level.txt
datacube-1.9.12.dist-info/RECORD
