Metadata-Version: 2.4
Name: datacube
Version: 1.9.12
Summary: An analysis environment for satellite and other earth observation data
License-Expression: Apache-2.0
Project-URL: Homepage, https://opendatacube.org/
Project-URL: Documentation, https://datacube-core.readthedocs.io/
Project-URL: Source, https://github.com/opendatacube/datacube-core/
Project-URL: Issues, https://github.com/opendatacube/datacube-core/issues
Project-URL: Chat, https://discord.com/invite/4hhBQVas5U
Classifier: Development Status :: 4 - Beta
Classifier: Intended Audience :: Developers
Classifier: Intended Audience :: Science/Research
Classifier: Natural Language :: English
Classifier: Operating System :: MacOS :: MacOS X
Classifier: Operating System :: POSIX
Classifier: Operating System :: POSIX :: BSD
Classifier: Operating System :: POSIX :: Linux
Classifier: Operating System :: Microsoft :: Windows
Classifier: Programming Language :: Python
Classifier: Programming Language :: Python :: 3
Classifier: Programming Language :: Python :: 3.10
Classifier: Programming Language :: Python :: 3.11
Classifier: Programming Language :: Python :: 3.12
Classifier: Programming Language :: Python :: 3.13
Classifier: Topic :: Scientific/Engineering :: GIS
Classifier: Topic :: Scientific/Engineering :: Information Analysis
Requires-Python: >=3.10
License-File: LICENSE
Requires-Dist: affine
Requires-Dist: alembic
Requires-Dist: antimeridian<0.4.5
Requires-Dist: attrs>=18.1
Requires-Dist: cachetools
Requires-Dist: click>=8
Requires-Dist: cloudpickle>=0.4
Requires-Dist: dask[array]
Requires-Dist: deprecat
Requires-Dist: distributed
Requires-Dist: GeoAlchemy2>=0.17.0
Requires-Dist: jsonschema>=4.18
Requires-Dist: lark
Requires-Dist: numpy>=1.26.0
Requires-Dist: odc-geo>=0.5.0
Requires-Dist: odc-loader>=0.6.0
Requires-Dist: odc-stac>=0.5.0
Requires-Dist: packaging
Requires-Dist: pandas
Requires-Dist: pyproj>=2.5
Requires-Dist: python-dateutil
Requires-Dist: pyyaml
Requires-Dist: rasterio>=1.3.11
Requires-Dist: ruamel.yaml
Requires-Dist: shapely>=2.0
Requires-Dist: sqlalchemy>=2.0
Requires-Dist: toolz
Requires-Dist: xarray>=0.9
Provides-Extra: performance
Requires-Dist: ciso8601; extra == "performance"
Requires-Dist: bottleneck; extra == "performance"
Provides-Extra: distributed
Requires-Dist: distributed; extra == "distributed"
Requires-Dist: dask[distributed]; extra == "distributed"
Provides-Extra: s3
Requires-Dist: boto3; extra == "s3"
Requires-Dist: botocore; extra == "s3"
Provides-Extra: netcdf
Requires-Dist: netcdf4; extra == "netcdf"
Provides-Extra: postgres
Requires-Dist: psycopg2; extra == "postgres"
Provides-Extra: psycopg3
Requires-Dist: psycopg; extra == "psycopg3"
Dynamic: license-file
